maturin-1.11.5.data/scripts/maturin
maturin-1.11.5.dist-info/METADATA
maturin-1.11.5.dist-info/WHEEL
maturin-1.11.5.dist-info/licenses/license-apache
maturin-1.11.5.dist-info/licenses/license-mit
maturin/__init__.py
maturin/__main__.py
maturin/bootstrap.py
maturin-1.11.5.dist-info/RECORD
