Metadata-Version: 2.4
Name: maturin
Version: 1.11.5
Classifier: Topic :: Software Development :: Build Tools
Classifier: Programming Language :: Rust
Classifier: Programming Language :: Python :: Implementation :: CPython
Classifier: Programming Language :: Python :: Implementation :: PyPy
Classifier: Programming Language :: Python :: Implementation :: GraalPy
Requires-Dist: tomli>=1.1.0 ; python_full_version < '3.11'
Requires-Dist: ziglang>=0.10.0,<0.13.0 ; extra == 'zig'
Requires-Dist: patchelf ; extra == 'patchelf'
Provides-Extra: zig
Provides-Extra: patchelf
License-File: license-mit
License-File: license-apache
Summary: Build and publish crates with pyo3, cffi and uniffi bindings as well as rust binaries as python packages
Home-Page: https://github.com/pyo3/maturin
Author-email: konstin <konstin@mailbox.org>
License-Expression: MIT OR Apache-2.0
Requires-Python: >=3.7
Project-URL: Source Code, https://github.com/PyO3/maturin
Project-URL: Issues, https://github.com/PyO3/maturin/issues
Project-URL: Documentation, https://maturin.rs
Project-URL: Changelog, https://maturin.rs/changelog.html
